LICENSE
README.md
setup.py
pyktree/__init__.py
pyktree.egg-info/PKG-INFO
pyktree.egg-info/SOURCES.txt
pyktree.egg-info/dependency_links.txt
pyktree.egg-info/top_level.txt
pyktree.egg-info/zip-safe
pyktree/nodes/__init__.py
pyktree/nodes/abc.py
pyktree/nodes/node.py
pyktree/walks/__init__.py
pyktree/walks/abc.py
pyktree/walks/data.py
pyktree/walks/reindex.py